Metadata-Version: 2.1
Name: auto_vicuna_plugin_template
Version: 0.0.1
Summary: The template plugin for Auto-Vicuna.
Project-URL: Homepage, https://github.com/BillSchumacher/Auto-Vicuna-Plugin-Template
Project-URL: Bug Tracker, https://github.com/BillSchumacher/Auto-Vicuna-Plugin-Template/issues
Author-email: Bill Schumacher <34168009+BillSchumacher@users.noreply.github.com>
License-File: LICENSE
Classifier: License :: OSI Approved :: MIT License
Classifier: Operating System :: OS Independent
Classifier: Programming Language :: Python :: 3
Requires-Python: >=3.9
Requires-Dist: abstract-singleton
